dump_things_pyclient/__init__.py
dump_things_pyclient/communicate.py
dump_things_pyclient/commands/__init__.py
dump_things_pyclient/commands/auto_curate.py
dump_things_pyclient/commands/get_records.py
dump_things_pyclient/commands/json2ttl.py
dump_things_pyclient/commands/post_records.py
dump_things_pyclient/commands/read_pages.py
dump_things_pyclient-0.1.3.dist-info/METADATA
dump_things_pyclient-0.1.3.dist-info/WHEEL
dump_things_pyclient-0.1.3.dist-info/entry_points.txt
dump_things_pyclient-0.1.3.dist-info/top_level.txt
dump_things_pyclient-0.1.3.dist-info/RECORD
