Metadata-Version: 2.4
Name: dump-things-pyclient
Version: 0.1.3
Summary: A client library and some CLI command for dump-things-services
Author-email: Christian Mönch <christian.moench@web.de>
Requires-Python: >=3.11
Requires-Dist: requests>=2.32.5
Provides-Extra: ttl
Requires-Dist: dump-things-service>=5.3.0; extra == "ttl"
Provides-Extra: tests
Requires-Dist: pytest>=9.0.1; extra == "tests"
